otoole/__init__.py
otoole/cli.py
otoole/convert.py
otoole/exceptions.py
otoole/input.py
otoole/read_strategies.py
otoole/utils.py
otoole/validate.py
otoole/validate.yaml
otoole/write_strategies.py
otoole/preprocess/__init__.py
otoole/preprocess/config.yaml
otoole/preprocess/longify_data.py
otoole/preprocess/setup.py
otoole/preprocess/validate_config.py
otoole/results/__init__.py
otoole/results/result_package.py
otoole/results/results.py
otoole/visualise/__init__.py
otoole/visualise/res.py
otoole-1.1.5.dist-info/LICENSE.txt
otoole-1.1.5.dist-info/METADATA
otoole-1.1.5.dist-info/WHEEL
otoole-1.1.5.dist-info/entry_points.txt
otoole-1.1.5.dist-info/top_level.txt
otoole-1.1.5.dist-info/RECORD
