Metadata-Version: 2.1
Name: otoole
Version: 1.1.5
Summary: A Python toolkit to support use of OSeMOSYS
Home-page: https://github.com/OSeMOSYS/otoole
Author: Will Usher
Author-email: wusher@kth.se
License: MIT
Project-URL: Documentation, https://otoole.readthedocs.io/en/latest/?badge=latest
Platform: any
Classifier: Development Status :: 4 - Beta
Classifier: Programming Language :: Python
Requires-Python: >=3.9
License-File: LICENSE.txt
Requires-Dist: xlrd
Requires-Dist: pyyaml
Requires-Dist: pydot
Requires-Dist: pandas>=2.1.4
Requires-Dist: Amply>=0.1.6
Requires-Dist: networkx
Requires-Dist: flatten-dict
Requires-Dist: openpyxl
Requires-Dist: pydantic>=2
Requires-Dist: importlib-metadata; python_version < "3.8"
Provides-Extra: testing
Requires-Dist: setuptools; extra == "testing"
Requires-Dist: pytest; extra == "testing"
Requires-Dist: pytest-cov; extra == "testing"
